nn_from_scratch/__init__.py
nn_from_scratch/functions.py
nn_from_scratch/nn.py
nn_from_scratch-0.4.2.dist-info/LICENCE.txt
nn_from_scratch-0.4.2.dist-info/METADATA
nn_from_scratch-0.4.2.dist-info/WHEEL
nn_from_scratch-0.4.2.dist-info/top_level.txt
nn_from_scratch-0.4.2.dist-info/RECORD
