Metadata-Version: 2.1
Name: nn-from-scratch
Version: 0.4.2
Summary: Neural Networks from Scratch
Home-page: https://github.com/ankush-003/torch-101
Author: Ankush H V
Author-email: anshhv2003@gmail.com
License: MIT
License-File: LICENCE.txt
Requires-Dist: fastapi
Requires-Dist: h5py
Requires-Dist: numpy
Requires-Dist: torch
Requires-Dist: gradio
Requires-Dist: ipywidgets
Requires-Dist: pillow
Requires-Dist: matplotlib
Requires-Dist: scikit-learn
Requires-Dist: scipy
Requires-Dist: seaborn
